{
  "hash": "041bf8b2",
  "configHash": "0cf3417e",
  "lockfileHash": "69ea6fe8",
  "browserHash": "5fa27f5e",
  "optimized": {
    "vue": {
      "src": "../../../node_modules/vue/dist/vue.runtime.esm-bundler.js",
      "file": "vue.js",
      "fileHash": "4efb7970",
      "needsInterop": false
    },
    "vitepress > @vue/devtools-api": {
      "src": "../../../node_modules/@vue/devtools-api/dist/index.js",
      "file": "vitepress___@vue_devtools-api.js",
      "fileHash": "1fab7071",
      "needsInterop": false
    },
    "vitepress > @vueuse/core": {
      "src": "../../../node_modules/@vueuse/core/dist/index.js",
      "file": "vitepress___@vueuse_core.js",
      "fileHash": "17a7b3d4",
      "needsInterop": false
    }
  },
  "chunks": {
    "chunk-DEFK5HPI": {
      "file": "chunk-DEFK5HPI.js"
    }
  }
}